commitizen_lrplugin/__init__.py
commitizen_lrplugin/lrplugin_version_provider.py
commitizen_lrplugin-0.1.1.dist-info/LICENSE
commitizen_lrplugin-0.1.1.dist-info/METADATA
commitizen_lrplugin-0.1.1.dist-info/WHEEL
commitizen_lrplugin-0.1.1.dist-info/entry_points.txt
commitizen_lrplugin-0.1.1.dist-info/RECORD
