Metadata-Version: 2.1
Name: commitizen-lrplugin
Version: 0.1.1
Summary: Commitizen version provider for Lua Lightroom plug-ins.
Author: Karsten Silkenbäumer
Author-email: 993392+kassi@users.noreply.github.com
Requires-Python: >=3.10,<4.0
Classifier: Programming Language :: Python :: 3
Classifier: Programming Language :: Python :: 3.10
Classifier: Programming Language :: Python :: 3.11
Classifier: Programming Language :: Python :: 3.12
